{
  "timestamps": [
    "2026-03-18T15:00:00.000Z",
    "2026-03-18T14:00:00.000Z",
    "2026-03-18T13:00:00.000Z"
  ],
  "extracted_pollutants": [
    {
      "o3_ppm": null,
      "no2_ppm": 0.022,
      "pm25": null
    },
    {
      "o3_ppm": 0.008,
      "no2_ppm": 0.025,
      "pm25": 2.8
    },
    {
      "o3_ppm": 0.021,
      "no2_ppm": 0.011,
      "pm25": 1.9
    }
  ],
  "pollutant_averages": {
    "o3_ppm": 0.0145,
    "no2_ppm": 0.01933333333333333,
    "pm25": 2.3499999999999996
  },
  "aqhi_raw": 2.49460700611866,
  "insufficient_data": false
}